unit_conversion/__init__.py
unit_conversion/unit_conversion.py
unit_conversion-1.0.2.dist-info/DESCRIPTION.rst
unit_conversion-1.0.2.dist-info/METADATA
unit_conversion-1.0.2.dist-info/RECORD
unit_conversion-1.0.2.dist-info/WHEEL
unit_conversion-1.0.2.dist-info/metadata.json
unit_conversion-1.0.2.dist-info/top_level.txt
