Metadata-Version: 2.0
Name: unit-conversion
Version: 1.0.2
Summary: Simple unit conversion API for python (milliseconds, seconds, minutes, hours, days)
Home-page: https://github.com/TheKewlStore/PyUnitConversion
Author: Ian Davis
Author-email: thekewlstore@gmail.com
License: UNKNOWN
Platform: UNKNOWN
